patchwork/__init__.py
patchwork/__main__.py
patchwork/app.py
patchwork/common/client/__init__.py
patchwork/common/client/llm/__init__.py
patchwork/common/client/llm/aio.py
patchwork/common/client/llm/anthropic.py
patchwork/common/client/llm/google_.py
patchwork/common/client/llm/openai_.py
patchwork/common/client/llm/protocol.py
patchwork/common/client/llm/utils.py
patchwork/common/client/patched.py
patchwork/common/client/scm.py
patchwork/common/client/sonar.py
patchwork/common/constants.py
patchwork/common/context_strategy/__init__.py
patchwork/common/context_strategy/context_strategies.py
patchwork/common/context_strategy/cpp.py
patchwork/common/context_strategy/generic.py
patchwork/common/context_strategy/java.py
patchwork/common/context_strategy/javascript.py
patchwork/common/context_strategy/kotlin.py
patchwork/common/context_strategy/languages.py
patchwork/common/context_strategy/position.py
patchwork/common/context_strategy/protocol.py
patchwork/common/context_strategy/python.py
patchwork/common/multiturn_strategy/__init__.py
patchwork/common/multiturn_strategy/agentic_strategy.py
patchwork/common/multiturn_strategy/agentic_strategy_v2.py
patchwork/common/multiturn_strategy/analyze_implement.py
patchwork/common/multiturn_strategy/multiturn_strategy.py
patchwork/common/multiturn_strategy/planning_strategy.py
patchwork/common/server.py
patchwork/common/tools/__init__.py
patchwork/common/tools/agentic_tools.py
patchwork/common/tools/api_tool.py
patchwork/common/tools/bash_tool.py
patchwork/common/tools/code_edit_tools.py
patchwork/common/tools/csvkit_tool.py
patchwork/common/tools/db_query_tool.py
patchwork/common/tools/git_tool.py
patchwork/common/tools/github_tool.py
patchwork/common/tools/grep_tool.py
patchwork/common/tools/tool.py
patchwork/common/utils/__init__.py
patchwork/common/utils/browser_initializer.py
patchwork/common/utils/dependency.py
patchwork/common/utils/filter_paths.py
patchwork/common/utils/input_parsing.py
patchwork_cli-0.0.124.dist-info/LICENSE
patchwork_cli-0.0.124.dist-info/METADATA
patchwork_cli-0.0.124.dist-info/WHEEL
patchwork_cli-0.0.124.dist-info/entry_points.txt
patchwork_cli-0.0.124.dist-info/RECORD
