Metadata-Version: 2.3
Name: patchwork-cli
Version: 0.0.124
Summary: 
License: AGPL
Author: patched.codes
Requires-Python: >=3.9,<4.0
Classifier: Development Status :: 3 - Alpha
Classifier: Environment :: Console
Classifier: Intended Audience :: Developers
Classifier: License :: OSI Approved :: GNU Affero General Public License v3 or later (AGPLv3+)
Classifier: License :: Other/Proprietary License
Classifier: Operating System :: OS Independent
Classifier: Programming Language :: Python :: 3
Classifier: Programming Language :: Python :: 3.9
Classifier: Programming Language :: Python :: 3.10
Classifier: Programming Language :: Python :: 3.11
Classifier: Programming Language :: Python :: 3.12
Classifier: Programming Language :: Python :: 3.13
Classifier: Topic :: Software Development :: Libraries :: Python Modules
Classifier: Topic :: Software Development :: Quality Assurance
Classifier: Topic :: Software Development :: Testing
Classifier: Topic :: Utilities
Provides-Extra: all
Provides-Extra: browser-use
Provides-Extra: notifications
Provides-Extra: security
Requires-Dist: anthropic (>=0.49.0,<0.50.0)
Requires-Dist: attrs (>=23.2.0,<23.3.0)
Requires-Dist: azure-devops (>=7.1.0b4,<7.2.0)
Requires-Dist: boto3 (>=1.37.11,<1.38.0)
Requires-Dist: browser-use (>=0.1.40,<0.2.0) ; (python_version >= "3.11") and (extra == "browser-use" or extra == "all")
Requires-Dist: chardet (>=5.2.0,<5.3.0)
Requires-Dist: chevron (>=0.14.0,<0.15.0)
Requires-Dist: click (>=8.1.0,<8.2.0)
Requires-Dist: csvkit (>=2.1.0,<3.0.0)
Requires-Dist: dotenv (>=0.9.9,<0.10.0)
Requires-Dist: eml_parser (>=2.0.0,<3.0.0)
Requires-Dist: gitpython (>=3.1.40,<3.2.0)
Requires-Dist: giturlparse (>=0.12.0,<0.13.0)
Requires-Dist: google-cloud-aiplatform (>=1.84.0,<2.0.0)
Requires-Dist: google-genai (>=1.2.0,<2.0.0)
Requires-Dist: json-repair (>=0.30.0,<0.31.0)
Requires-Dist: langchain-anthropic (>=0.3.3,<0.4.0) ; extra == "browser-use" or extra == "all"
Requires-Dist: langchain-google-genai (>=2.0.10,<3.0.0) ; extra == "browser-use" or extra == "all"
Requires-Dist: langchain-openai (>=0.3.1,<0.4.0) ; extra == "browser-use" or extra == "all"
Requires-Dist: libcst (>=1.1.0,<1.2.0)
Requires-Dist: numpy (==1.26.4)
Requires-Dist: openai (>=1.46.1,<2.0.0)
Requires-Dist: owasp-depscan (==5.2.15) ; extra == "security" or extra == "all"
Requires-Dist: packageurl-python (>=0.15.0,<0.16.0)
Requires-Dist: pandas (==2.2.3)
Requires-Dist: patched-code2prompt (>=0.9.0.dev1,<0.10.0)
Requires-Dist: pillow (>=10.4.0,<10.5.0) ; extra == "browser-use" or extra == "all"
Requires-Dist: playwright (>=1.50.0,<1.51.0) ; extra == "browser-use" or extra == "all"
Requires-Dist: pydantic (>=2.10.6,<2.11.0)
Requires-Dist: pydantic-ai (>=0.0.37,<0.0.38)
Requires-Dist: pygithub (>=2.1.1,<2.2.0)
Requires-Dist: python-gitlab (>=4.13.0,<5.0.0)
Requires-Dist: python-magic (>=0.4.27,<0.5.0)
Requires-Dist: pyyaml (>=6.0.1,<7.0.0)
Requires-Dist: requests (>=2.32.3,<2.33.0)
Requires-Dist: rich (>=13.7.1,<13.8.0)
Requires-Dist: scikit-learn (>=1.3.2,<2.0.0)
Requires-Dist: scipy (==1.13.1)
Requires-Dist: semgrep (==1.52.0) ; extra == "security" or extra == "all"
Requires-Dist: semver (>=3.0.2,<3.1.0)
Requires-Dist: slack-sdk (>=3.28.0,<3.29.0) ; extra == "notifications" or extra == "all"
Requires-Dist: sqlalchemy (>=2.0.36,<2.1.0)
Requires-Dist: tree-sitter (>=0.21.3,<0.22.0)
Requires-Dist: tree-sitter-languages (>=1.10.2,<1.11.0)
Requires-Dist: typing-extensions (>=4.11.0,<5.0.0)
